[
{ "seq_id" : 128, "qsl_idx" : 17213, "data" : "FD020000" },
{ "seq_id" : 129, "qsl_idx" : 49764, "data" : "A9010000" },
{ "seq_id" : 130, "qsl_idx" : 6413, "data" : "C3030000" },
{ "seq_id" : 131, "qsl_idx" : 2828, "data" : "9F010000" },
{ "seq_id" : 132, "qsl_idx" : 22856, "data" : "B1000000" },
{ "seq_id" : 133, "qsl_idx" : 20850, "data" : "44010000" },
{ "seq_id" : 134, "qsl_idx" : 49017, "data" : "23010000" },
{ "seq_id" : 135, "qsl_idx" : 34600, "data" : "93010000" },
{ "seq_id" : 136, "qsl_idx" : 8094, "data" : "30000000" },
{ "seq_id" : 137, "qsl_idx" : 33088, "data" : "B0030000" },
{ "seq_id" : 138, "qsl_idx" : 8900, "data" : "95000000" },
{ "seq_id" : 139, "qsl_idx" : 28951, "data" : "EF010000" },
{ "seq_id" : 140, "qsl_idx" : 15679, "data" : "A0010000" },
{ "seq_id" : 141, "qsl_idx" : 43536, "data" : "6A000000" },
{ "seq_id" : 142, "qsl_idx" : 2227, "data" : "18000000" },
{ "seq_id" : 143, "qsl_idx" : 18061, "data" : "18000000" },
{ "seq_id" : 144, "qsl_idx" : 26810, "data" : "61000000" },
{ "seq_id" : 145, "qsl_idx" : 46796, "data" : "0D000000" },
{ "seq_id" : 146, "qsl_idx" : 26862, "data" : "C1000000" },
{ "seq_id" : 147, "qsl_idx" : 1260, "data" : "CB020000" },
{ "seq_id" : 148, "qsl_idx" : 39998, "data" : "D4030000" },
{ "seq_id" : 149, "qsl_idx" : 38119, "data" : "AD010000" },
{ "seq_id" : 150, "qsl_idx" : 25620, "data" : "3A030000" },
{ "seq_id" : 151, "qsl_idx" : 49280, "data" : "C5000000" },
{ "seq_id" : 152, "qsl_idx" : 18533, "data" : "68020000" },
{ "seq_id" : 153, "qsl_idx" : 12453, "data" : "A5030000" },
{ "seq_id" : 154, "qsl_idx" : 25588, "data" : "3E010000" },
{ "seq_id" : 155, "qsl_idx" : 26924, "data" : "76000000" },
{ "seq_id" : 156, "qsl_idx" : 47799, "data" : "66010000" },
{ "seq_id" : 157, "qsl_idx" : 16304, "data" : "69020000" },
{ "seq_id" : 158, "qsl_idx" : 37237, "data" : "13020000" },
{ "seq_id" : 159, "qsl_idx" : 21755, "data" : "B0000000" },
{ "seq_id" : 160, "qsl_idx" : 31871, "data" : "73030000" },
{ "seq_id" : 161, "qsl_idx" : 35085, "data" : "72000000" },
{ "seq_id" : 162, "qsl_idx" : 41829, "data" : "D8010000" },
{ "seq_id" : 163, "qsl_idx" : 7121, "data" : "31000000" },
{ "seq_id" : 164, "qsl_idx" : 44105, "data" : "DB010000" },
{ "seq_id" : 165, "qsl_idx" : 42150, "data" : "99020000" },
{ "seq_id" : 166, "qsl_idx" : 32542, "data" : "C0010000" },
{ "seq_id" : 167, "qsl_idx" : 28395, "data" : "C7030000" },
{ "seq_id" : 168, "qsl_idx" : 34611, "data" : "3C000000" },
{ "seq_id" : 169, "qsl_idx" : 32056, "data" : "82020000" },
{ "seq_id" : 170, "qsl_idx" : 18797, "data" : "30020000" },
{ "seq_id" : 171, "qsl_idx" : 16570, "data" : "92000000" },
{ "seq_id" : 172, "qsl_idx" : 1198, "data" : "26010000" },
{ "seq_id" : 173, "qsl_idx" : 5760, "data" : "7D010000" },
{ "seq_id" : 174, "qsl_idx" : 2156, "data" : "79000000" },
{ "seq_id" : 175, "qsl_idx" : 47874, "data" : "50010000" },
{ "seq_id" : 176, "qsl_idx" : 21818, "data" : "7D000000" },
{ "seq_id" : 177, "qsl_idx" : 43987, "data" : "36020000" },
{ "seq_id" : 178, "qsl_idx" : 35501, "data" : "5C000000" },
{ "seq_id" : 179, "qsl_idx" : 31671, "data" : "A9000000" },
{ "seq_id" : 180, "qsl_idx" : 11588, "data" : "44010000" },
{ "seq_id" : 181, "qsl_idx" : 12397, "data" : "4A020000" },
{ "seq_id" : 182, "qsl_idx" : 22151, "data" : "55010000" },
{ "seq_id" : 183, "qsl_idx" : 16960, "data" : "A3030000" },
{ "seq_id" : 184, "qsl_idx" : 13746, "data" : "2F020000" },
{ "seq_id" : 185, "qsl_idx" : 32748, "data" : "0D010000" },
{ "seq_id" : 186, "qsl_idx" : 33908, "data" : "E9000000" },
{ "seq_id" : 187, "qsl_idx" : 9412, "data" : "7C030000" },
{ "seq_id" : 188, "qsl_idx" : 6663, "data" : "04010000" },
{ "seq_id" : 189, "qsl_idx" : 15015, "data" : "DB020000" },
{ "seq_id" : 190, "qsl_idx" : 30677, "data" : "13010000" },
{ "seq_id" : 191, "qsl_idx" : 27170, "data" : "2A030000" },
{ "seq_id" : 384, "qsl_idx" : 9742, "data" : "C1010000" },
{ "seq_id" : 385, "qsl_idx" : 27662, "data" : "D1010000" },
{ "seq_id" : 386, "qsl_idx" : 26710, "data" : "90000000" },
{ "seq_id" : 387, "qsl_idx" : 12454, "data" : "7B000000" },
{ "seq_id" : 388, "qsl_idx"

...

: "BD030000" },
{ "seq_id" : 49662, "qsl_idx" : 36847, "data" : "09030000" },
{ "seq_id" : 49663, "qsl_idx" : 27800, "data" : "A2010000" },
{ "seq_id" : 49856, "qsl_idx" : 45145, "data" : "99010000" },
{ "seq_id" : 49857, "qsl_idx" : 32474, "data" : "58020000" },
{ "seq_id" : 49858, "qsl_idx" : 8818, "data" : "17000000" },
{ "seq_id" : 49859, "qsl_idx" : 11198, "data" : "DC010000" },
{ "seq_id" : 49860, "qsl_idx" : 12744, "data" : "F0000000" },
{ "seq_id" : 49861, "qsl_idx" : 35025, "data" : "84000000" },
{ "seq_id" : 49862, "qsl_idx" : 42933, "data" : "59020000" },
{ "seq_id" : 49863, "qsl_idx" : 15823, "data" : "14020000" },
{ "seq_id" : 49864, "qsl_idx" : 26395, "data" : "99020000" },
{ "seq_id" : 49865, "qsl_idx" : 33455, "data" : "FA010000" },
{ "seq_id" : 49866, "qsl_idx" : 15270, "data" : "3E010000" },
{ "seq_id" : 49867, "qsl_idx" : 34722, "data" : "08020000" },
{ "seq_id" : 49868, "qsl_idx" : 5988, "data" : "44020000" },
{ "seq_id" : 49869, "qsl_idx" : 47387, "data" : "DB030000" },
{ "seq_id" : 49870, "qsl_idx" : 15366, "data" : "AE030000" },
{ "seq_id" : 49871, "qsl_idx" : 5403, "data" : "ED000000" },
{ "seq_id" : 49872, "qsl_idx" : 1530, "data" : "7A000000" },
{ "seq_id" : 49873, "qsl_idx" : 15915, "data" : "E2030000" },
{ "seq_id" : 49874, "qsl_idx" : 30712, "data" : "50000000" },
{ "seq_id" : 49875, "qsl_idx" : 33403, "data" : "EC000000" },
{ "seq_id" : 49876, "qsl_idx" : 32947, "data" : "9B000000" },
{ "seq_id" : 49877, "qsl_idx" : 5444, "data" : "1C020000" },
{ "seq_id" : 49878, "qsl_idx" : 29392, "data" : "88000000" },
{ "seq_id" : 49879, "qsl_idx" : 18045, "data" : "E7000000" },
{ "seq_id" : 49880, "qsl_idx" : 39477, "data" : "20000000" },
{ "seq_id" : 49881, "qsl_idx" : 16266, "data" : "01030000" },
{ "seq_id" : 49882, "qsl_idx" : 27338, "data" : "A2030000" },
{ "seq_id" : 49883, "qsl_idx" : 36603, "data" : "D4020000" },
{ "seq_id" : 49884, "qsl_idx" : 8030, "data" : "F8020000" },
{ "seq_id" : 49885, "qsl_idx" : 43867, "data" : "69030000" },
{ "seq_id" : 49886, "qsl_idx" : 49190, "data" : "6F000000" },
{ "seq_id" : 49887, "qsl_idx" : 24796, "data" : "9F030000" },
{ "seq_id" : 49888, "qsl_idx" : 19667, "data" : "26020000" },
{ "seq_id" : 49889, "qsl_idx" : 18351, "data" : "53020000" },
{ "seq_id" : 49890, "qsl_idx" : 1250, "data" : "B6010000" },
{ "seq_id" : 49891, "qsl_idx" : 28785, "data" : "F7000000" },
{ "seq_id" : 49892, "qsl_idx" : 30447, "data" : "61000000" },
{ "seq_id" : 49893, "qsl_idx" : 7296, "data" : "7B010000" },
{ "seq_id" : 49894, "qsl_idx" : 29904, "data" : "66030000" },
{ "seq_id" : 49895, "qsl_idx" : 21101, "data" : "85020000" },
{ "seq_id" : 49896, "qsl_idx" : 17508, "data" : "BE000000" },
{ "seq_id" : 49897, "qsl_idx" : 26089, "data" : "5E000000" },
{ "seq_id" : 49898, "qsl_idx" : 26802, "data" : "CD000000" },
{ "seq_id" : 49899, "qsl_idx" : 3174, "data" : "AB020000" },
{ "seq_id" : 49900, "qsl_idx" : 26899, "data" : "66030000" },
{ "seq_id" : 49901, "qsl_idx" : 36027, "data" : "6B000000" },
{ "seq_id" : 49902, "qsl_idx" : 14777, "data" : "1E030000" },
{ "seq_id" : 49903, "qsl_idx" : 38257, "data" : "2F020000" },
{ "seq_id" : 49904, "qsl_idx" : 27678, "data" : "CD020000" },
{ "seq_id" : 49905, "qsl_idx" : 33515, "data" : "41030000" },
{ "seq_id" : 49906, "qsl_idx" : 32918, "data" : "BD030000" },
{ "seq_id" : 49907, "qsl_idx" : 18623, "data" : "19030000" },
{ "seq_id" : 49908, "qsl_idx" : 30716, "data" : "FB020000" },
{ "seq_id" : 49909, "qsl_idx" : 16899, "data" : "95030000" },
{ "seq_id" : 49910, "qsl_idx" : 39816, "data" : "25020000" },
{ "seq_id" : 49911, "qsl_idx" : 3525, "data" : "8B000000" },
{ "seq_id" : 49912, "qsl_idx" : 1932, "data" : "6A000000" },
{ "seq_id" : 49913, "qsl_idx" : 19718, "data" : "AA000000" },
{ "seq_id" : 49914, "qsl_idx" : 13645, "data" : "6D030000" },
{ "seq_id" : 49915, "qsl_idx" : 34911, "data" : "45030000" },
{ "seq_id" : 49916, "qsl_idx" : 29348, "data" : "74030000" },
{ "seq_id" : 49917, "qsl_idx" : 3065, "data" : "77020000" },
{ "seq_id" : 49918, "qsl_idx" : 8736, "data" : "8F000000" },
{ "seq_id" : 49919, "qsl_idx" : 15384, "data" : "84030000" }
]
